odoo/addons/mail_environment/README.rst
odoo/addons/mail_environment/__init__.py
odoo/addons/mail_environment/__manifest__.py
odoo/addons/mail_environment/i18n/de.po
odoo/addons/mail_environment/i18n/es.po
odoo/addons/mail_environment/i18n/fr.po
odoo/addons/mail_environment/i18n/hr.po
odoo/addons/mail_environment/i18n/it.po
odoo/addons/mail_environment/i18n/mail_environment.pot
odoo/addons/mail_environment/i18n/pt_BR.po
odoo/addons/mail_environment/i18n/sl.po
odoo/addons/mail_environment/i18n/sv.po
odoo/addons/mail_environment/i18n/zh_CN.po
odoo/addons/mail_environment/models/__init__.py
odoo/addons/mail_environment/models/fetchmail_server.py
odoo/addons/mail_environment/models/ir_mail_server.py
odoo/addons/mail_environment/readme/CONFIGURE.md
odoo/addons/mail_environment/readme/CONTRIBUTORS.md
odoo/addons/mail_environment/readme/DESCRIPTION.md
odoo/addons/mail_environment/readme/INSTALL.md
odoo/addons/mail_environment/readme/ROADMAP.md
odoo/addons/mail_environment/readme/USAGE.md
odoo/addons/mail_environment/static/description/icon.png
odoo/addons/mail_environment/static/description/index.html
odoo/addons/mail_environment/tests/__init__.py
odoo/addons/mail_environment/tests/test_mail_environment.py
odoo_addon_mail_environment-18.0.1.0.1.3.dist-info/METADATA
odoo_addon_mail_environment-18.0.1.0.1.3.dist-info/WHEEL
odoo_addon_mail_environment-18.0.1.0.1.3.dist-info/top_level.txt
odoo_addon_mail_environment-18.0.1.0.1.3.dist-info/RECORD
